ps_opt/__init__.py
ps_opt/_base.py
ps_opt/_error.py
ps_opt/_feature_selection_process.py
ps_opt/_hyperparameters_tuning_process.py
ps_opt/feature_selection.py
ps_opt/hyperparameters_tuning.py
ps_opt/search_space_characteristics.py
ps_optimize-2.0.4.dist-info/METADATA
ps_optimize-2.0.4.dist-info/WHEEL
ps_optimize-2.0.4.dist-info/top_level.txt
ps_optimize-2.0.4.dist-info/RECORD
